autopath/__init__.py
autopath-0.0.0.dist-info/METADATA
autopath-0.0.0.dist-info/WHEEL
autopath-0.0.0.dist-info/top_level.txt
autopath-0.0.0.dist-info/RECORD
